contrastiveIR/__init__.py
contrastiveIR/cir.py
contrastiveIR-1.0.4.dist-info/LICENSE
contrastiveIR-1.0.4.dist-info/METADATA
contrastiveIR-1.0.4.dist-info/WHEEL
contrastiveIR-1.0.4.dist-info/top_level.txt
contrastiveIR-1.0.4.dist-info/RECORD
