Metadata-Version: 2.1
Name: contrastiveIR
Version: 1.0.4
License-File: LICENSE
Requires-Dist: numpy >=1.24.3
Requires-Dist: pandas >=2.1.4
Requires-Dist: scipy >=1.9.3
